fhnw/__init__.py
fhnw/nlp/__init__.py
fhnw/nlp/utils/__init__.py
fhnw/nlp/utils/colab.py
fhnw/nlp/utils/defaults.py
fhnw/nlp/utils/helpers.py
fhnw/nlp/utils/image_helpers.py
fhnw/nlp/utils/normalize.py
fhnw/nlp/utils/params.py
fhnw/nlp/utils/ploting.py
fhnw/nlp/utils/preprocess.py
fhnw/nlp/utils/processing.py
fhnw/nlp/utils/storage.py
fhnw/nlp/utils/system.py
fhnw/nlp/utils/text.py
fhnw/nlp/utils/transformers.py
fhnw_nlp_utils-0.11.0.dist-info/METADATA
fhnw_nlp_utils-0.11.0.dist-info/WHEEL
fhnw_nlp_utils-0.11.0.dist-info/top_level.txt
fhnw_nlp_utils-0.11.0.dist-info/RECORD
