Metadata-Version: 2.1
Name: fhnw-nlp-utils
Version: 0.11.0
Summary: Utilities for NLP courses taught at FHNW.
Home-page: http://github.com/markif/fhnw-nlp-utils
Author: Fabian
License: MIT
Platform: UNKNOWN
Requires-Dist: numpy
Requires-Dist: pandas
Requires-Dist: psutil
Requires-Dist: multiprocess
Requires-Dist: wget
Requires-Dist: gdown
Requires-Dist: scikit-learn
Requires-Dist: nltk
Requires-Dist: matplotlib
Requires-Dist: wordcloud
Requires-Dist: compound-split
Requires-Dist: pyarrow
Requires-Dist: iterative-stratification
